[
  {
    "id": 1,
    "code": "0",
    "description": "None"
  },
  {
    "id": 2,
    "code": "C01",
    "description": "Coating - epoxy coated"
  },
  {
    "id": 3,
    "code": "C02",
    "description": "Coating - galvanized"
  },
  {
    "id": 4,
    "code": "C03",
    "description": "Coating - metalized"
  },
  {
    "id": 5,
    "code": "CX",
    "description": "Coating - other"
  },
  {
    "id": 6,
    "code": "R01",
    "description": "Reinforcing - stainless, clad"
  },
  {
    "id": 7,
    "code": "R02",
    "description": "Reinforcing - stainless, solid"
  },
  {
    "id": 8,
    "code": "R03",
    "description": "Reinforcing - high chromium"
  },
  {
    "id": 9,
    "code": "R04",
    "description": "Reinforcing - FRP, aramid fiber"
  },
  {
    "id": 10,
    "code": "R05",
    "description": "Reinforcing - FRP, carbon fiber"
  },
  {
    "id": 11,
    "code": "R06",
    "description": "Reinforcing - FRP, glass fiber"
  },
  {
    "id": 12,
    "code": "R07",
    "description": "Reinforcing - FRP, other"
  },
  {
    "id": 13,
    "code": "RX",
    "description": "Reinforcing - other"
  },
  {
    "id": 14,
    "code": "S01",
    "description": "Sacrificial - cathodic, passive"
  },
  {
    "id": 15,
    "code": "S02",
    "description": "Sacrificial - cathodic, active"
  },
  {
    "id": 16,
    "code": "SX",
    "description": "Sacrificial - other"
  },
  {
    "id": 17,
    "code": "U",
    "description": "Unknown"
  },
  {
    "id": 18,
    "code": "X",
    "description": "Other"
  },
  {
    "id": 19,
    "code": "C-T",
    "description": "Temporary Code"
  },
  {
    "id": 20,
    "code": "S-T",
    "description": "Temporary Code"
  },
  {
    "id": 21,
    "code": "X-T",
    "description": "Temporary Code"
  }
]